Workbook

Sheet Assumptions
A1: Balance Sheet Assumptions
A2: (blue cells are authored inputs)
A3: Opening Cash ($000) | B3: 18000
A4: Opening Accounts Receivable | B4: 9000
A5: Opening Inventory | B5: 7000
A6: Opening Prepaid Expenses | B6: 1500
A7: Opening Gross PP&E | B7: 40000
A8: Opening Accumulated Deprec. | B8: 12000
A9: Goodwill | B9: 15000
A10: Intangible Assets | B10: 6000
A11: Opening Accounts Payable | B11: 6500
A12: Opening Accrued Expenses | B12: 3000
A13: Opening Deferred Revenue | B13: 2500
A14: Opening Short-term Debt | B14: 5000
... A22: AP Growth per Year | B22: 400

Sheet BalanceSheet
A1: Balance Sheet (USD $000)
A2: ($ in thousands) | B2: FY20 | C2: FY21 | D2: FY22 | E2: FY23 | F2: FY24 | G2: FY25 | H2: FY26
A3: ASSETS
A4: Cash & Equivalents | B4: =Assumptions!$B$3 -> 18000 | C4: =B4+Assumptions!$B$19+(C10-B10)-Assumptions!$B$17+Assumptions!$B$17-Assumptions!$B$20-Assumptions!$B$21+Assumptions!$B$22 -> 27700 | D4: =C4+Assumptions!$B$19+(D10-C10)-Assumptions!$B$17+Assumptions!$B$17-Assumptions!$B$20-Assumptions!$B$21+Assumptions!$B$22 -> 37800 | E4: =D4+Assumptions!$B$19+(E10-D10)-Assumptions!$B$17+Assumptions!$B$17-Assumptions!$B$20-Assumptions!$B$21+Assumptions!$B$22 -> 48300 | F4: =E4+Assumptions!$B$19+(F10-E10)-Assumptions!$B$17+Assumptions!$B$17-Assumptions!$B$20-Assumptions!$B$21+Assumptions!$B$22 -> 59200 | G4: =F4+Assumptions!$B$19+(G10-F10)-Assumptions!$B$17+Assumptions!$B$17-Assumptions!$B$20-Assumptions!$B$21+Assumptions!$B$22 -> 70500 | H4: =G4+Assumptions!$B$19+(H10-G10)-Assumptions!$B$17+Assumptions!$B$17-Assumptions!$B$20-Assumptions!$B$21+Assumptions!$B$22 -> 82200
A5: Accounts Receivable | B5: =Assumptions!$B$4 -> 9000 | C5: =B5+Assumptions!$B$20 -> 9600 | D5: =C5+Assumptions!$B$20 -> 10200 | E5: =D5+Assumptions!$B$20 -> 10800 | F5: =E5+Assumptions!$B$20 -> 11400 | G5: =F5+Assumptions!$B$20 -> 12000 | H5: =G5+Assumptions!$B$20 -> 12600
A6: Inventory | B6: =Assumptions!$B$5 -> 7000 | C6: =B6+Assumptions!$B$21 -> 7500 | D6: =C6+Assumptions!$B$21 -> 8000 | E6: =D6+Assumptions!$B$21 -> 8500 | F6: =E6+Assumptions!$B$21 -> 9000 | G6: =F6+Assumptions!$B$21 -> 9500 | H6: =G6+Assumptions!$B$21 -> 10000
A7: Prepaid Expenses | B7: =Assumptions!$B$6 -> 1500 | C7: =B7 -> 1500 | D7: =C7 -> 1500 | E7: =D7 -> 1500 | F7: =E7 -> 1500 | G7: =F7 -> 1500 | H7: =G7 -> 1500
A8: Total Current Assets | B8: =SUM(B4:B7) -> 35500 | C8: =SUM(C4:C7) -> 46300 | D8: =SUM(D4:D7) -> 57500 | E8: =SUM(E4:E7) -> 69100 | F8: =SUM(F4:F7) -> 81100 | G8: =SUM(G4:G7) -> 93500 | H8: =SUM(H4:H7) -> 106300
A9: Gross PP&E | B9: =Assumptions!$B$7 -> 40000 | C9: =B9+Assumptions!$B$17 -> 44000 | D9: =C9+Assumptions!$B$17 -> 48000 | E9: =D9+Assumptions!$B$17 -> 52000 | F9: =E9+Assumptions!$B$17 -> 56000 | G9: =F9+Assumptions!$B$17 -> 60000 | H9: =G9+Assumptions!$B$17 -> 64000
A10: Less: Accumulated Depreciation | B10: =Assumptions!$B$8 -> 12000 | C10: =B10+C9*Assumptions!$B$18 -> 16400 | D10: =C10+D9*Assumptions!$B$18 -> 21200 | E10: =D10+E9*Assumptions!$B$18 -> 26400 | F10: =E10+F9*Assumptions!$B$18 -> 32000 | G10: =F10+G9*Assumptions!$B$18 -> 38000 | H10: =G10+H9*Assumptions!$B$18 -> 44400
A11: Net PP&E | B11: =B9-B10 -> 28000 | C11: =C9-C10 -> 27600 | D11: =D9-D10 -> 26800 | E11: =E9-E10 -> 25600 | F11: =F9-F10 -> 24000 | G11: =G9-G10 -> 22000 | H11: =H9-H10 -> 19600
A12: Goodwill | B12: =Assumptions!$B$9 -> 15000 | C12: =B12 -> 15000 | D12: =C12 -> 15000 | E12: =D12 -> 15000 | F12: =E12 -> 15000 | G12: =F12 -> 15000 | H12: =G12 -> 15000
A13: Intangible Assets | B13: =Assumptions!$B$10 -> 6000 | C13: =B13 -> 6000 | D13: =C13 -> 6000 | E13: =D13 -> 6000 | F13: =E13 -> 6000 | G13: =F13 -> 6000 | H13: =G13 -> 6000
A14: Total Non-Current Assets | B14: =B11+B12+B13 -> 49000 | C14: =C11+C12+C13 -> 48600 | D14: =D11+D12+D13 -> 47800 | E14: =E11+E12+E13 -> 46600 | F14: =F11+F12+F13 -> 45000 | G14: =G11+G12+G13 -> 43000 | H14: =H11+H12+H13 -> 40600
A15: Total Assets | B15: =B8+B14 -> 84500 | C15: =C8+C14 -> 94900 | D15: =D8+D14 -> 105300 | E15: =E8+E14 -> 115700 | F15: =F8+F14 -> 126100 | G15: =G8+G14 -> 136500 | H15: =H8+H14 -> 146900
A16: LIABILITIES
A17: Accounts Payable | B17: =Assumptions!$B$11 -> 6500 | C17: =B17+Assumptions!$B$22 -> 6900 | D17: =C17+Assumptions!$B$22 -> 7300 | E17: =D17+Assumptions!$B$22 -> 7700 | F17: =E17+Assumptions!$B$22 -> 8100 | G17: =F17+Assumptions!$B$22 -> 8500 | H17: =G17+Assumptions!$B$22 -> 8900
A18: Accrued Expenses | B18: =Assumptions!$B$12 -> 3000 | C18: =B18 -> 3000 | D18: =C18 -> 3000 | E18: =D18 -> 3000 | F18: =E18 -> 3000 | G18: =F18 -> 3000 | H18: =G18 -> 3000
A19: Deferred Revenue | B19: =Assumptions!$B$13 -> 2500 | C19: =B19 -> 2500 | D19: =C19 -> 2500 | E19: =D19 -> 2500 | F19: =E19 -> 2500 | G19: =F19 -> 2500 | H19: =G19 -> 2500
A20: Short-term Debt | B20: =Assumptions!$B$14 -> 5000 | C20: =B20 -> 5000 | D20: =C20 -> 5000 | E20: =D20 -> 5000 | F20: =E20 -> 5000 | G20: =F20 -> 5000 | H20: =G20 -> 5000
A21: Total Current Liabilities | B21: =SUM(B17:B20) -> 17000 | C21: =SUM(C17:C20) -> 17400 | D21: =SUM(D17:D20) -> 17800 | E21: =SUM(E17:E20) -> 18200 | F21: =SUM(F17:F20) -> 18600 | G21: =SUM(G17:G20) -> 19000 | H21: =SUM(H17:H20) -> 19400
A22: Long-term Debt | B22: =Assumptions!$B$15 -> 22000 | C22: =B22+Assumptions!$B$17 -> 26000 | D22: =C22+Assumptions!$B$17 -> 30000 | E22: =D22+Assumptions!$B$17 -> 34000 | F22: =E22+Assumptions!$B$17 -> 38000 | G22: =F22+Assumptions!$B$17 -> 42000 | H22: =G22+Assumptions!$B$17 -> 46000
A23: Total Liabilities | B23: =B21+B22 -> 39000 | C23: =C21+C22 -> 43400 | D23: =D21+D22 -> 47800 | E23: =E21+E22 -> 52200 | F23: =F21+F22 -> 56600 | G23: =G21+G22 -> 61000 | H23: =H21+H22 -> 65400
A24: EQUITY
A25: Common Stock | B25: =Assumptions!$B$16 -> 30000 | C25: =B25 -> 30000 | D25: =C25 -> 30000 | E25: =D25 -> 30000 | F25: =E25 -> 30000 | G25: =F25 -> 30000 | H25: =G25 -> 30000
A26: Retained Earnings | B26: =(B8+B14)-B23-B25 -> 15500 | C26: =B26+Assumptions!$B$19 -> 21500 | D26: =C26+Assumptions!$B$19 -> 27500 | E26: =D26+Assumptions!$B$19 -> 33500 | F26: =E26+Assumptions!$B$19 -> 39500 | G26: =F26+Assumptions!$B$19 -> 45500 | H26: =G26+Assumptions!$B$19 -> 51500
A27: Total Equity | B27: =B25+B26 -> 45500 | C27: =C25+C26 -> 51500 | D27: =D25+D26 -> 57500 | E27: =E25+E26 -> 63500 | F27: =F25+F26 -> 69500 | G27: =G25+G26 -> 75500 | H27: =H25+H26 -> 81500
A28: Total Liabilities & Equity | B28: =B23+B27 -> 84500 | C28: =C23+C27 -> 94900 | D28: =D23+D27 -> 105300 | E28: =E23+E27 -> 115700 | F28: =F23+F27 -> 126100 | G28: =G23+G27 -> 136500 | H28: =H23+H27 -> 146900
A29: Balance Check (A - L&E) | B29: =B15-B28 -> 0 | C29: =C15-C28 -> 0 | D29: =D15-D28 -> 0 | E29: =E15-E28 -> 0 | F29: =F15-F28 -> 0 | G29: =G15-G28 -> 0 | H29: =H15-H28 -> 0
