Workbook

Sheet Assumptions
A1: Assumptions
A3: Base Revenue (2023A) | B3: 42000
A4: Revenue Growth % | B4: 0.12
A5: COGS % of Revenue | B5: 0.58
A6: SG&A % of Revenue | B6: 0.17
A7: R&D % of Revenue | B7: 0.09
A8: Interest Expense | B8: 1200
A9: Tax Rate | B9: 0.24

Sheet P&L
A1: Income Statement ($000s)
B2: 2023A | C2: 2024E | D2: 2025E
A3: Revenue | B3: =Assumptions!B3 -> 42000 | C3: =B3*(1+Assumptions!B4) -> 47040 | D3: =C3*(1+Assumptions!B4) -> 52684.8
A4: Cost of Goods Sold | B4: =B3*Assumptions!B5 -> 24360 | C4: =C3*Assumptions!B5 -> 27283.2 | D4: =D3*Assumptions!B5 -> 30557.184
A5: Gross Profit | B5: =B3-B4 -> 17640 | C5: =C3-C4 -> 19756.8 | D5: =D3-D4 -> 22127.616
A6: SG&A | B6: =B3*Assumptions!B6 -> 7140 | C6: =C3*Assumptions!B6 -> 7996.8 | D6: =D3*Assumptions!B6 -> 8956.416
A7: Research & Development | B7: =B3*Assumptions!B7 -> 3780 | C7: =C3*Assumptions!B7 -> 4233.6 | D7: =D3*Assumptions!B7 -> 4741.632
A8: Total Operating Expenses | B8: =B6+B7 -> 10920 | C8: =C6+C7 -> 12230.4 | D8: =D6+D7 -> 13698.048
A9: Operating Income (EBIT) | B9: =B5-B8 -> 6720 | C9: =C5-C8 -> 7526.4 | D9: =D5-D8 -> 8429.568
A10: Interest Expense | B10: =Assumptions!B8 -> 1200 | C10: =Assumptions!B8 -> 1200 | D10: =Assumptions!B8 -> 1200
A11: Pretax Income | B11: =B9-B10 -> 5520 | C11: =C9-C10 -> 6326.4 | D11: =D9-D10 -> 7229.568
A12: Income Tax | B12: =B11*Assumptions!B9 -> 1324.8 | C12: =C11*Assumptions!B9 -> 1518.336 | D12: =D11*Assumptions!B9 -> 1735.0963
A13: Net Income | B13: =B11-B12 -> 4195.2 | C13: =C11-C12 -> 4808.064 | D13: =D11-D12 -> 5494.4717
A15: Gross Margin % | B15: =B5/B3 -> 0.42 | C15: =C5/C3 -> 0.42 | D15: =D5/D3 -> 0.42
A16: Operating Margin % | B16: =B9/B3 -> 0.16 | C16: =C9/C3 -> 0.16 | D16: =D9/D3 -> 0.16
A17: Net Margin % | B17: =B13/B3 -> 0.099885714 | C17: =C13/C3 -> 0.10221224 | D17: =D13/D3 -> 0.1042895
