Workbook

Sheet Assumptions
A1: Assumptions & Drivers
A2: (blue cells are authored inputs)
A3: Base Revenue (FY20, $000) | B3: 42000
A4: Revenue Growth % | B4: 0.16
A5: Gross Margin % | B5: 0.62
A6: SG&A % of Revenue | B6: 0.14
A7: R&D % of Revenue | B7: 0.09
A8: Marketing % of Revenue | B8: 0.07
A9: G&A % of Revenue | B9: 0.05
A10: D&A % of Revenue | B10: 0.04
A11: Interest Rate on Debt | B11: 0.06
A12: Debt Balance ($000) | B12: 20000
A13: Tax Rate | B13: 0.24

Sheet P&L
A1: Income Statement (USD $000)
A2: ($ in thousands) | B2: FY20 | C2: FY21 | D2: FY22 | E2: FY23 | F2: FY24 | G2: FY25 | H2: FY26 | I2: FY27
A3: Revenue | B3: =Assumptions!$B$3 -> 42000 | C3: =B3*(1+Assumptions!$B$4) -> 48720 | D3: =C3*(1+Assumptions!$B$4) -> 56515.2 | E3: =D3*(1+Assumptions!$B$4) -> 65557.632 | F3: =E3*(1+Assumptions!$B$4) -> 76046.853 | G3: =F3*(1+Assumptions!$B$4) -> 88214.35 | H3: =G3*(1+Assumptions!$B$4) -> 102328.65 | I3: =H3*(1+Assumptions!$B$4) -> 118701.23
A4: Cost of Goods Sold | B4: =B3*(1-Assumptions!$B$5) -> 15960 | C4: =C3*(1-Assumptions!$B$5) -> 18513.6 | D4: =D3*(1-Assumptions!$B$5) -> 21475.776 | E4: =E3*(1-Assumptions!$B$5) -> 24911.9 | F4: =F3*(1-Assumptions!$B$5) -> 28897.804 | G4: =G3*(1-Assumptions!$B$5) -> 33521.453 | H4: =H3*(1-Assumptions!$B$5) -> 38884.885 | I4: =I3*(1-Assumptions!$B$5) -> 45106.467
A5: Gross Profit | B5: =B3-B4 -> 26040 | C5: =C3-C4 -> 30206.4 | D5: =D3-D4 -> 35039.424 | E5: =E3-E4 -> 40645.732 | F5: =F3-F4 -> 47149.049 | G5: =G3-G4 -> 54692.897 | H5: =H3-H4 -> 63443.76 | I5: =I3-I4 -> 73594.762
A6: SG&A | B6: =B3*Assumptions!$B$6 -> 5880 | C6: =C3*Assumptions!$B$6 -> 6820.8 | D6: =D3*Assumptions!$B$6 -> 7912.128 | E6: =E3*Assumptions!$B$6 -> 9178.0685 | F6: =F3*Assumptions!$B$6 -> 10646.559 | G6: =G3*Assumptions!$B$6 -> 12350.009 | H6: =H3*Assumptions!$B$6 -> 14326.01 | I6: =I3*Assumptions!$B$6 -> 16618.172
A7: Research & Development | B7: =B3*Assumptions!$B$7 -> 3780 | C7: =C3*Assumptions!$B$7 -> 4384.8 | D7: =D3*Assumptions!$B$7 -> 5086.368 | E7: =E3*Assumptions!$B$7 -> 5900.1869 | F7: =F3*Assumptions!$B$7 -> 6844.2168 | G7: =G3*Assumptions!$B$7 -> 7939.2915 | H7: =H3*Assumptions!$B$7 -> 9209.5781 | I7: =I3*Assumptions!$B$7 -> 10683.111
A8: Marketing | B8: =B3*Assumptions!$B$8 -> 2940 | C8: =C3*Assumptions!$B$8 -> 3410.4 | D8: =D3*Assumptions!$B$8 -> 3956.064 | E8: =E3*Assumptions!$B$8 -> 4589.0342 | F8: =F3*Assumptions!$B$8 -> 5323.2797 | G8: =G3*Assumptions!$B$8 -> 6175.0045 | H8: =H3*Assumptions!$B$8 -> 7163.0052 | I8: =I3*Assumptions!$B$8 -> 8309.086
A9: General & Administrative | B9: =B3*Assumptions!$B$9 -> 2100 | C9: =C3*Assumptions!$B$9 -> 2436 | D9: =D3*Assumptions!$B$9 -> 2825.76 | E9: =E3*Assumptions!$B$9 -> 3277.8816 | F9: =F3*Assumptions!$B$9 -> 3802.3427 | G9: =G3*Assumptions!$B$9 -> 4410.7175 | H9: =H3*Assumptions!$B$9 -> 5116.4323 | I9: =I3*Assumptions!$B$9 -> 5935.0614
A10: Total Operating Expenses | B10: =SUM(B6:B9) -> 14700 | C10: =SUM(C6:C9) -> 17052 | D10: =SUM(D6:D9) -> 19780.32 | E10: =SUM(E6:E9) -> 22945.171 | F10: =SUM(F6:F9) -> 26616.399 | G10: =SUM(G6:G9) -> 30875.022 | H10: =SUM(H6:H9) -> 35815.026 | I10: =SUM(I6:I9) -> 41545.43
A11: EBITDA | B11: =B5-B10 -> 11340 | C11: =C5-C10 -> 13154.4 | D11: =D5-D10 -> 15259.104 | E11: =E5-E10 -> 17700.561 | F11: =F5-F10 -> 20532.65 | G11: =G5-G10 -> 23817.874 | H11: =H5-H10 -> 27628.734 | I11: =I5-I10 -> 32049.332
A12: Depreciation & Amortization | B12: =B3*Assumptions!$B$10 -> 1680 | C12: =C3*Assumptions!$B$10 -> 1948.8 | D12: =D3*Assumptions!$B$10 -> 2260.608 | E12: =E3*Assumptions!$B$10 -> 2622.3053 | F12: =F3*Assumptions!$B$10 -> 3041.8741 | G12: =G3*Assumptions!$B$10 -> 3528.574 | H12: =H3*Assumptions!$B$10 -> 4093.1458 | I12: =I3*Assumptions!$B$10 -> 4748.0492
A13: Operating Income (EBIT) | B13: =B11-B12 -> 9660 | C13: =C11-C12 -> 11205.6 | D13: =D11-D12 -> 12998.496 | E13: =E11-E12 -> 15078.255 | F13: =F11-F12 -> 17490.776 | G13: =G11-G12 -> 20289.3 | H13: =H11-H12 -> 23535.588 | I13: =I11-I12 -> 27301.283
A14: Interest Expense | B14: =Assumptions!$B$12*Assumptions!$B$11 -> 1200 | C14: =Assumptions!$B$12*Assumptions!$B$11 -> 1200 | D14: =Assumptions!$B$12*Assumptions!$B$11 -> 1200 | E14: =Assumptions!$B$12*Assumptions!$B$11 -> 1200 | F14: =Assumptions!$B$12*Assumptions!$B$11 -> 1200 | G14: =Assumptions!$B$12*Assumptions!$B$11 -> 1200 | H14: =Assumptions!$B$12*Assumptions!$B$11 -> 1200 | I14: =Assumptions!$B$12*Assumptions!$B$11 -> 1200
A15: Pretax Income | B15: =B13-B14 -> 8460 | C15: =C13-C14 -> 10005.6 | D15: =D13-D14 -> 11798.496 | E15: =E13-E14 -> 13878.255 | F15: =F13-F14 -> 16290.776 | G15: =G13-G14 -> 19089.3 | H15: =H13-H14 -> 22335.588 | I15: =I13-I14 -> 26101.283
A16: Income Tax | B16: =B15*Assumptions!$B$13 -> 2030.4 | C16: =C15*Assumptions!$B$13 -> 2401.344 | D16: =D15*Assumptions!$B$13 -> 2831.639 | E16: =E15*Assumptions!$B$13 -> 3330.7813 | F16: =F15*Assumptions!$B$13 -> 3909.7863 | G16: =G15*Assumptions!$B$13 -> 4581.4321 | H16: =H15*Assumptions!$B$13 -> 5360.5412 | I16: =I15*Assumptions!$B$13 -> 6264.3078
A17: Net Income | B17: =B15-B16 -> 6429.6 | C17: =C15-C16 -> 7604.256 | D17: =D15-D16 -> 8966.857 | E17: =E15-E16 -> 10547.474 | F17: =F15-F16 -> 12380.99 | G17: =G15-G16 -> 14507.868 | H17: =H15-H16 -> 16975.047 | I17: =I15-I16 -> 19836.975
A18: Gross Margin % | B18: =B5/B3 -> 0.62 | C18: =C5/C3 -> 0.62 | D18: =D5/D3 -> 0.62 | E18: =E5/E3 -> 0.62 | F18: =F5/F3 -> 0.62 | G18: =G5/G3 -> 0.62 | H18: =H5/H3 -> 0.62 | I18: =I5/I3 -> 0.62
A19: EBITDA Margin % | B19: =B11/B3 -> 0.27 | C19: =C11/C3 -> 0.27 | D19: =D11/D3 -> 0.27 | E19: =E11/E3 -> 0.27 | F19: =F11/F3 -> 0.27 | G19: =G11/G3 -> 0.27 | H19: =H11/H3 -> 0.27 | I19: =I11/I3 -> 0.27
A20: Net Margin % | B20: =B17/B3 -> 0.15308571 | C20: =C17/C3 -> 0.15608079 | D20: =D17/D3 -> 0.15866275 | E20: =E17/E3 -> 0.16088858 | F20: =F17/F3 -> 0.16280739 | G20: =G17/G3 -> 0.16446155 | H20: =H17/H3 -> 0.16588754 | I20: =I17/I3 -> 0.16711684
