Workbook

Sheet Assumptions
A1: Project Atlas — LBO Assumptions
A3: Transaction
A4: Entry EV / EBITDA | B4: 9
A5: Exit EV / EBITDA | B5: 9.5
A6: Entry Net Debt / EBITDA | B6: 4.5
A7: Hold Period (years) | B7: 5
A9: Operating
A10: Entry Revenue ($mm) | B10: 500
A11: Revenue Growth (% p.a.) | B11: 0.08
A12: Entry EBITDA Margin (%) | B12: 0.22
A13: Exit EBITDA Margin (%) | B13: 0.25
A15: Financing
A16: Interest Rate on Debt (%) | B16: 0.075
A17: Mandatory Debt Paydown (% p.a.) | B17: 0.1
A18: Tax Rate (%) | B18: 0.25

Sheet P&L
A1: P&L Projection ($mm)
A3: Year | B3: Y0 | C3: Y1 | D3: Y2 | E3: Y3 | F3: Y4 | G3: Y5
A4: Revenue | B4: =Assumptions!B10 -> 500 | C4: =B4*(1+Assumptions!$B$11) -> 540 | D4: =C4*(1+Assumptions!$B$11) -> 583.2 | E4: =D4*(1+Assumptions!$B$11) -> 629.856 | F4: =E4*(1+Assumptions!$B$11) -> 680.24448 | G4: =F4*(1+Assumptions!$B$11) -> 734.66404
A5: EBITDA Margin | B5: =Assumptions!$B$12+(Assumptions!$B$13-Assumptions!$B$12)*0/Assumptions!$B$7 -> 0.22 | C5: =Assumptions!$B$12+(Assumptions!$B$13-Assumptions!$B$12)*1/Assumptions!$B$7 -> 0.226 | D5: =Assumptions!$B$12+(Assumptions!$B$13-Assumptions!$B$12)*2/Assumptions!$B$7 -> 0.232 | E5: =Assumptions!$B$12+(Assumptions!$B$13-Assumptions!$B$12)*3/Assumptions!$B$7 -> 0.238 | F5: =Assumptions!$B$12+(Assumptions!$B$13-Assumptions!$B$12)*4/Assumptions!$B$7 -> 0.244 | G5: =Assumptions!$B$12+(Assumptions!$B$13-Assumptions!$B$12)*5/Assumptions!$B$7 -> 0.25
A6: EBITDA | B6: =B4*B5 -> 110 | C6: =C4*C5 -> 122.04 | D6: =D4*D5 -> 135.3024 | E6: =E4*E5 -> 149.90573 | F6: =F4*F5 -> 165.97965 | G6: =G4*G5 -> 183.66601
A7: Less: D&A (4% rev) | B7: =-B4*0.04 -> -20 | C7: =-C4*0.04 -> -21.6 | D7: =-D4*0.04 -> -23.328 | E7: =-E4*0.04 -> -25.19424 | F7: =-F4*0.04 -> -27.209779 | G7: =-G4*0.04 -> -29.386562
A8: EBIT | B8: =B6+B7 -> 90 | C8: =C6+C7 -> 100.44 | D8: =D6+D7 -> 111.9744 | E8: =E6+E7 -> 124.71149 | F8: =F6+F7 -> 138.76987 | G8: =G6+G7 -> 154.27945
A9: Less: Interest | B9: 0 | C9: =-Debt!C4*Assumptions!$B$16 -> -33.4125 | D9: =-Debt!D4*Assumptions!$B$16 -> -30.07125 | E9: =-Debt!E4*Assumptions!$B$16 -> -27.064125 | F9: =-Debt!F4*Assumptions!$B$16 -> -24.357713 | G9: =-Debt!G4*Assumptions!$B$16 -> -21.921941
A10: EBT | B10: =B8+B9 -> 90 | C10: =C8+C9 -> 67.0275 | D10: =D8+D9 -> 81.90315 | E10: =E8+E9 -> 97.647363 | F10: =F8+F9 -> 114.41216 | G10: =G8+G9 -> 132.35751
A11: Less: Tax | B11: =-MAX(B10,0)*Assumptions!$B$18 -> -22.5 | C11: =-MAX(C10,0)*Assumptions!$B$18 -> -16.756875 | D11: =-MAX(D10,0)*Assumptions!$B$18 -> -20.475787 | E11: =-MAX(E10,0)*Assumptions!$B$18 -> -24.411841 | F11: =-MAX(F10,0)*Assumptions!$B$18 -> -28.60304 | G11: =-MAX(G10,0)*Assumptions!$B$18 -> -33.089377
A12: Net Income | B12: =B10+B11 -> 67.5 | C12: =C10+C11 -> 50.270625 | D12: =D10+D11 -> 61.427363 | E12: =E10+E11 -> 73.235522 | F12: =F10+F11 -> 85.809121 | G12: =G10+G11 -> 99.26813

Sheet Debt
A1: Debt Schedule ($mm)
A3: Year | B3: Y0 | C3: Y1 | D3: Y2 | E3: Y3 | F3: Y4 | G3: Y5
A4: Opening Debt | B4: =Assumptions!B6*'P&L'!B6 -> 495 | C4: =B5 -> 445.5 | D4: =C5 -> 400.95 | E4: =D5 -> 360.855 | F4: =E5 -> 324.7695 | G4: =F5 -> 292.29255
A5: Closing Debt | B5: =B4*(1-Assumptions!$B$17) -> 445.5 | C5: =C4*(1-Assumptions!$B$17) -> 400.95 | D5: =D4*(1-Assumptions!$B$17) -> 360.855 | E5: =E4*(1-Assumptions!$B$17) -> 324.7695 | F5: =F4*(1-Assumptions!$B$17) -> 292.29255 | G5: =G4*(1-Assumptions!$B$17) -> 263.06329

Sheet Returns
A1: Returns Summary
A3: Entry EBITDA | B3: ='P&L'!B6 -> 110
A4: Entry EV | B4: =Assumptions!B4*B3 -> 990
A5: Entry Net Debt | B5: =Debt!B4 -> 495
A6: Entry Equity | B6: =B4-B5 -> 495
A8: Exit EBITDA | B8: ='P&L'!G6 -> 183.66601
A9: Exit EV | B9: =Assumptions!B5*B8 -> 1744.8271
A10: Exit Net Debt | B10: =Debt!G5 -> 263.06329
A11: Exit Equity | B11: =B9-B10 -> 1481.7638
A13: MOIC | B13: =B11/B6 -> 2.9934622
A14: IRR | B14: =(B11/B6)^(1/Assumptions!B7)-1 -> 0.24518751
